workflow_uva/__init__.py
workflow_uva-0.2.5.dist-info/LICENSE
workflow_uva-0.2.5.dist-info/METADATA
workflow_uva-0.2.5.dist-info/WHEEL
workflow_uva-0.2.5.dist-info/top_level.txt
workflow_uva-0.2.5.dist-info/RECORD
