Metadata-Version: 2.1
Name: workflow-uva
Version: 0.2.5
Summary: A workflow for Canvas and Nbgrader
Home-page: https://github.com/jaspervdh96/Workflow
Author: Jasper van der Heide
Author-email: jaspervdh96@hotmail.com
License: UNKNOWN
Platform: UNKNOWN
Classifier: Programming Language :: Python :: 3
Classifier: License :: OSI Approved :: MIT License
Classifier: Operating System :: OS Independent
Requires-Dist: beautifulsoup4 (>=4.7.1)
Requires-Dist: canvasapi (>=0.12.0)
Requires-Dist: ipython (>=6.2.1)
Requires-Dist: ipywidgets (>=7.4.2)
Requires-Dist: matplotlib (>=2.2.2)
Requires-Dist: nbconvert (>=5.5.0)
Requires-Dist: nbgrader (>=0.6.1)
Requires-Dist: nbstripout (>=0.3.6)
Requires-Dist: numpy (>=1.16.4)
Requires-Dist: pandas (>=1.0.1)
Requires-Dist: requests (>=2.22.0)
Requires-Dist: seaborn (>=0.9.0)
Requires-Dist: tqdm (>=4.32.2)
Requires-Dist: traitlets (>=4.3.2)
